windget/__init__.py
windget/wsd.py
windget/wsee.py
windget/wses.py
windget/wsi.py
windget/wsq.py
windget/wss.py
windget/wst.py
windget-0.0.7.dist-info/LICENSE
windget-0.0.7.dist-info/METADATA
windget-0.0.7.dist-info/WHEEL
windget-0.0.7.dist-info/top_level.txt
windget-0.0.7.dist-info/RECORD
