Metadata-Version: 2.1
Name: windget
Version: 0.0.7
Summary: windget a is third party Win.D API for python.
Home-page: https://windget-doc.readthedocs.io/zh/latest/
Author: Syuya_Murakami
Author-email: wxy135@mail.ustc.edu.cn
Project-URL: Bug Tracker, https://windget-doc.readthedocs.io/zh/latest/
Classifier: Programming Language :: Python :: 3
Classifier: License :: OSI Approved :: MIT License
Classifier: Operating System :: OS Independent
Requires-Python: >=3.6
License-File: LICENSE
